yandexgptlite/__init__.py
yandexgptlite/yandexgptlite.py
yandexgptlite-0.1.7.dist-info/LICENSE.txt
yandexgptlite-0.1.7.dist-info/METADATA
yandexgptlite-0.1.7.dist-info/WHEEL
yandexgptlite-0.1.7.dist-info/top_level.txt
yandexgptlite-0.1.7.dist-info/RECORD
