Metadata-Version: 2.1
Name: yandexgptlite
Version: 0.1.7
Summary: Получение ответов от YandexGPT Lite
Home-page: https://github.com/morinad/yandexgptlite
Author: Александр Морин
Author-email: y.director@yandex.ru
License-File: LICENSE.txt
Requires-Dist: requests
